cfdverify/__init__.py
cfdverify/discretization.py
cfdverify/utils.py
cfdverify-0.0.2.dist-info/METADATA
cfdverify-0.0.2.dist-info/WHEEL
cfdverify-0.0.2.dist-info/licenses/LICENSE
cfdverify-0.0.2.dist-info/RECORD
