Metadata-Version: 2.4
Name: cfdverify
Version: 0.0.2
Summary: A package to conduct solution verification for CFD
Project-URL: Homepage, https://github.com/ORNL/cfd-verify
Project-URL: Issues, https://github.com/ORNL/cfd-verify/issues
Author-email: Justin Weinmeister <weinmeistejr@ornl.gov>
License-Expression: MIT
License-File: LICENSE
Classifier: License :: OSI Approved :: MIT License
Classifier: Operating System :: OS Independent
Classifier: Programming Language :: Python :: 3
Requires-Python: >=3.8
Requires-Dist: matplotlib
Requires-Dist: numpy
Requires-Dist: pandas
Requires-Dist: scipy
Provides-Extra: docs
Requires-Dist: sphinx; extra == 'docs'
Requires-Dist: sphinx-rtd-theme; extra == 'docs'
Provides-Extra: full
Requires-Dist: pytest; extra == 'full'
Requires-Dist: sphinx; extra == 'full'
Requires-Dist: sphinx-rtd-theme; extra == 'full'
Provides-Extra: tests
Requires-Dist: pytest; extra == 'tests'
